brokkr_diagnostics/__init__.py
brokkr_diagnostics/__main__.py
brokkr_diagnostics/build_binary.py
brokkr_diagnostics/runner.py
brokkr_diagnostics/confidential_compute/__init__.py
brokkr_diagnostics/confidential_compute/toggle.py
brokkr_diagnostics/console/__init__.py
brokkr_diagnostics/console/commands.py
brokkr_diagnostics/console/interactive.py
brokkr_diagnostics/console/ui.py
brokkr_diagnostics/core/__init__.py
brokkr_diagnostics/core/cuda.py
brokkr_diagnostics/core/executor.py
brokkr_diagnostics/core/models.py
brokkr_diagnostics/core/reader.py
brokkr_diagnostics/infiniband/__init__.py
brokkr_diagnostics/infiniband/config.py
brokkr_diagnostics/infiniband/diagnostics.py
brokkr_diagnostics/infiniband/models.py
brokkr_diagnostics/kernel/__init__.py
brokkr_diagnostics/kernel/logs.py
brokkr_diagnostics/kernel/services.py
brokkr_diagnostics/kernel/sysinfo.py
brokkr_diagnostics/nvidia/__init__.py
brokkr_diagnostics/nvidia/cuda_tests.py
brokkr_diagnostics/nvidia/driver.py
brokkr_diagnostics/nvidia/driver_models.py
brokkr_diagnostics/nvidia/hardware.py
brokkr_diagnostics/nvidia/models.py
brokkr_diagnostics/nvidia/reset.py
brokkr_diagnostics/pcie/__init__.py
brokkr_diagnostics/pcie/config.py
brokkr_diagnostics/pcie/diagnostics.py
brokkr_diagnostics-0.3.5.dist-info/METADATA
brokkr_diagnostics-0.3.5.dist-info/WHEEL
brokkr_diagnostics-0.3.5.dist-info/entry_points.txt
brokkr_diagnostics-0.3.5.dist-info/top_level.txt
brokkr_diagnostics-0.3.5.dist-info/RECORD
