Metadata-Version: 2.4
Name: brokkr-diagnostics
Version: 0.3.5
Summary: NVIDIA GPU and InfiniBand diagnostics toolkit
Author-email: Brokkr <fabricio.policarpo@hydrahost.com>
License: MIT
Classifier: Programming Language :: Python :: 3
Classifier: Programming Language :: Python :: 3.8
Classifier: Programming Language :: Python :: 3.10
Classifier: License :: OSI Approved :: MIT License
Classifier: Operating System :: POSIX :: Linux
Requires-Python: >=3.8
Requires-Dist: numpy>=1.24.4
Requires-Dist: nvidia-gpu-admin-tools>=2025.11.21
Requires-Dist: termcolor>=2.4.0
Requires-Dist: prompt_toolkit>=3.0.0
Provides-Extra: dev
Requires-Dist: pyinstaller>=6.0.0; extra == "dev"
